LICENSE
README.md
setup.py
validacao/__init__.py
validacao/validacao.py
validacao.egg-info/PKG-INFO
validacao.egg-info/SOURCES.txt
validacao.egg-info/dependency_links.txt
validacao.egg-info/top_level.txt